ipydoodle/__init__.py
ipydoodle/ipydoodle.py
ipydoodle-0.1.2.dist-info/METADATA
ipydoodle-0.1.2.dist-info/WHEEL
ipydoodle-0.1.2.dist-info/top_level.txt
ipydoodle-0.1.2.dist-info/RECORD
