Metadata-Version: 2.1
Name: ipydoodle
Version: 0.1.2
Requires-Dist: ipycanvas (==0.12.0)
